.travis.yml
AUTHORS
CHANGELOG.md
ChangeLog
LICENSE
Makefile
README.md
requirements.txt
requirements_testing.txt
setup.cfg
setup.py
bandit_high_entropy_string.egg-info/PKG-INFO
bandit_high_entropy_string.egg-info/SOURCES.txt
bandit_high_entropy_string.egg-info/dependency_links.txt
bandit_high_entropy_string.egg-info/entry_points.txt
bandit_high_entropy_string.egg-info/not-zip-safe
bandit_high_entropy_string.egg-info/pbr.json
bandit_high_entropy_string.egg-info/requires.txt
bandit_high_entropy_string.egg-info/top_level.txt
bandit_plugins/__init__.py
bandit_plugins/bandit_high_entropy_string.py