Metadata-Version: 1.0
Name: bandit-high-entropy-string
Version: 2.1.2
Summary: A bandit plugin to check for strings that have high entropy (possible hardcoded secrets).
Home-page: UNKNOWN
Author: Ryan Lane
Author-email: rlane@lyft.com
License: Apache-2
Platform: UNKNOWN
